xhm_config/.gitignore
xhm_config/README.md
xhm_config/__init__.py
xhm_config/application.toml
xhm_config/config.py
xhm_config/llm_config.py
xhm_config/sdk_secrets.toml
xhm_config/sdk_settings.toml
xhm_log/README.md
xhm_log/__init__.py
xhm_base-0.0.9.dist-info/METADATA
xhm_base-0.0.9.dist-info/WHEEL
xhm_base-0.0.9.dist-info/RECORD
